hangpy/__init__.py
hangpy/ascii_status.py
hangpy/game.py
hangpy/main.py
hangpy/translations.py
hangpy/utils.py
hangpy/data/dics/en.txt
hangpy/data/dics/es.txt
hangpy_cli-0.1.3.dist-info/LICENSE
hangpy_cli-0.1.3.dist-info/METADATA
hangpy_cli-0.1.3.dist-info/WHEEL
hangpy_cli-0.1.3.dist-info/entry_points.txt
hangpy_cli-0.1.3.dist-info/top_level.txt
hangpy_cli-0.1.3.dist-info/RECORD
