Metadata-Version: 2.1
Name: hangpy-cli
Version: 0.1.3
Summary: CLI program to play the hangman game suporting multiple languages, ideal for learning new words
Home-page: https://github.com/renzofbn/hangpy
Author: Renzo Valentin
Author-email: renzofbn@gmail.com
Keywords: hangpy,hangman,game,cli,command-line,hangman-game
Classifier: Programming Language :: Python :: 3
Classifier: License :: OSI Approved :: MIT License
Classifier: Operating System :: OS Independent
Classifier: Topic :: Games/Entertainment :: Puzzle Games
Requires-Python: >=3.6
License-File: LICENSE
